[
  {
    "job_url": "https://www.linkedin.com/jobs/view/4399054807",
    "session_id": "2026-04-10T22:13:19Z",
    "company": "IBM",
    "date_posted": null,
    "level": "Entry",
    "location": "Austin, TX",
    "max_exp": null,
    "min_exp": null,
    "pipeline": "important",
    "priority_score": 102,
    "score_pct": 78,
    "site": "linkedin",
    "summary": "**Introduction** Ready to grow your career in the Cloud?",
    "title": "Software Developer"
  },
  {
    "job_url": "https://www.linkedin.com/jobs/view/4400606542",
    "session_id": "2026-04-10T22:13:19Z",
    "company": "MongoDB",
    "date_posted": null,
    "level": "Entry",
    "location": "New York, NY",
    "max_exp": null,
    "min_exp": null,
    "pipeline": "important",
    "priority_score": 46,
    "score_pct": 35,
    "site": "linkedin",
    "summary": "The MongoDB Cloud Services Team is a diverse group of contributors working together to help our users manage MongoDB at global scale.",
    "title": "Software Engineer 3"
  },
  {
    "job_url": "https://www.linkedin.com/jobs/view/4387888835",
    "session_id": "2026-04-10T22:13:19Z",
    "company": "Lyft",
    "date_posted": null,
    "level": "Entry",
    "location": "San Francisco County, CA",
    "max_exp": 3.0,
    "min_exp": 3.0,
    "pipeline": "important",
    "priority_score": 35,
    "score_pct": 27,
    "site": "linkedin",
    "summary": "At Lyft, our purpose is to serve and connect.",
    "title": "Software Engineer, Lyft Business"
  },
  {
    "job_url": "https://www.linkedin.com/jobs/view/4399061471",
    "session_id": "2026-04-10T22:13:19Z",
    "company": "Chime",
    "date_posted": null,
    "level": "Entry",
    "location": "San Francisco, CA",
    "max_exp": null,
    "min_exp": null,
    "pipeline": "important",
    "priority_score": 29,
    "score_pct": 22,
    "site": "linkedin",
    "summary": "**About The Role** Chime\u2019s Instant Loans team builds products that give members upfront liquidity for larger, specific needs, with clear, predictable repayment that helps them build credit responsibl\u2026",
    "title": "Software Engineer, Instant Loans"
  },
  {
    "job_url": "https://www.linkedin.com/jobs/view/4372860143",
    "session_id": "2026-04-10T22:13:19Z",
    "company": "Broadcom",
    "date_posted": null,
    "level": "Entry",
    "location": "Lisle, IL",
    "max_exp": null,
    "min_exp": null,
    "pipeline": "important",
    "priority_score": 28,
    "score_pct": 22,
    "site": "linkedin",
    "summary": "**Job Description:** **Job Description Summary** **Experienced Software Development Engineer** : Plans, designs, develops and tests software systems or applications for software enhancements and fixe\u2026",
    "title": "Mainframe Software Development Engineer"
  },
  {
    "job_url": "https://www.linkedin.com/jobs/view/4398167876",
    "session_id": "2026-04-10T22:13:19Z",
    "company": "Twitch",
    "date_posted": null,
    "level": "Mid",
    "location": "San Francisco, CA",
    "max_exp": null,
    "min_exp": null,
    "pipeline": "important",
    "priority_score": -999,
    "score_pct": 0,
    "site": "linkedin",
    "summary": "**About Us** Twitch is the world\u2019s biggest live streaming service, with global communities built around gaming, entertainment, music, sports, cooking, and more.",
    "title": "Software Engineer II, Safety"
  }
]